{
  "projetos": [
    {
      "id": 1,
      "nome": "Aplicando API"
    },
    {
      "nome": "Treinamento",
      "id": 3
    },
    {
      "id": 4,
      "nome": "Estutado Padrões de Projeto"
    },
    {
      "nome": "Treinamento 2.0",
      "id": 5
    }
  ],
  "tarefas": [
    {
      "duracaoEmSegundos": 0,
      "descricao": "Melhorando em API",
      "projeto": {
        "id": 1,
        "nome": "Aplicando API"
      },
      "id": 2
    },
    {
      "duracaoEmSegundos": 1,
      "descricao": {
        "__v_isShallow": true,
        "dep": {
          "w": 100,
          "n": 1
        },
        "__v_isRef": true,
        "_rawValue": "Oi",
        "_value": "Oi"
      },
      "id": 3
    },
    {
      "mutations": {},
      "actions": {},
      "id": 4
    }
  ]
}